PYEVALB/__init__.py
PYEVALB/__main__.py
PYEVALB/parser.py
PYEVALB/scorer.py
PYEVALB/summary.py
PYEVALB/tree.py
PYEVALB-0.1.3.dist-info/DESCRIPTION.rst
PYEVALB-0.1.3.dist-info/METADATA
PYEVALB-0.1.3.dist-info/RECORD
PYEVALB-0.1.3.dist-info/WHEEL
PYEVALB-0.1.3.dist-info/entry_points.txt
PYEVALB-0.1.3.dist-info/metadata.json
PYEVALB-0.1.3.dist-info/top_level.txt
