Metadata-Version: 2.0
Name: PYEVALB
Version: 0.1.3
Summary: Scoring tools for bracket tree banks.
Home-page: https://github.com/flyaway1217/PYEVALB
Author: Flyaway
Author-email: flyaway1217@gmail.com
License: GNU
Keywords: score bracket tree banks
Platform: UNKNOWN
Classifier: Development Status :: 3 - Alpha
Classifier: License :: OSI Approved :: GNU Lesser General Public License v3 (LGPLv3)
Classifier: Intended Audience :: Developers
Classifier: Topic :: Software Development :: Build Tools
Classifier: Programming Language :: Python :: 3.2
Classifier: Programming Language :: Python :: 3.3
Classifier: Programming Language :: Python :: 3.4
Classifier: Programming Language :: Python :: 3.5
Requires-Dist: pytablewriter (>=0.10.2)
